scraping_items_package/__init__.py
scraping_items_package/tools/__init__.py
scraping_items_package/tools/autodoc_scraping.py
scraping_items_package/tools/create_response.py
scraping_items_package/tools/onlinecarparts_scraping.py
scraping_items_package/tools/scraping_tool.py
scraping_items_package/tools/utils.py
scraping_items_package/yamls/scraping_tool.yaml
tests/__init__.py
tests/test_scraping_tool.py
scraping_items_package-0.0.1.dist-info/METADATA
scraping_items_package-0.0.1.dist-info/WHEEL
scraping_items_package-0.0.1.dist-info/entry_points.txt
scraping_items_package-0.0.1.dist-info/top_level.txt
scraping_items_package-0.0.1.dist-info/RECORD
