Metadata-Version: 2.1
Name: scraping_items_package
Version: 0.0.1
Summary: This is my tools package
